kanaconv
