Metadata-Version: 1.1
Name: kanaconv
Version: 1.0.1
Summary: Converts hiragana and katakana to rōmaji according to Modified Hepburn transliteration rules
Home-page: https://github.com/msikma/kanaconv
Author: Michiel Sikma
Author-email: michiel@sikma.org
License: MIT
Platform: UNKNOWN
Classifier: Intended Audience :: Developers
Classifier: Intended Audience :: Education
Classifier: License :: OSI Approved :: MIT License
Classifier: Natural Language :: Japanese
Classifier: Topic :: Software Development :: Libraries :: Python Modules
Classifier: Topic :: Text Processing :: Linguistic
Classifier: Programming Language :: Python :: 2.7
Classifier: Programming Language :: Python :: 3.4
